AioKeksik/__init__.py
AioKeksik/api.py
AioKeksik-1.2.dist-info/LICENSE.md
AioKeksik-1.2.dist-info/METADATA
AioKeksik-1.2.dist-info/WHEEL
AioKeksik-1.2.dist-info/top_level.txt
AioKeksik-1.2.dist-info/RECORD
