Metadata-Version: 2.1
Name: AioKeksik
Version: 1.2
Summary: Неофициальная асинхронная библиотека для работы с API https://keksik.io
Home-page: https://github.com/Obnovlator3000/AioKeksik
Author: Obnovlator3000
Author-email: obnovlator3000@lisi4ka.ru
License: MIT
License-File: LICENSE.md
Requires-Dist: aiohttp
Requires-Dist: ujson
